odoo/addons/account_fiscal_position_rule_sale/README.rst
odoo/addons/account_fiscal_position_rule_sale/__init__.py
odoo/addons/account_fiscal_position_rule_sale/__manifest__.py
odoo/addons/account_fiscal_position_rule_sale/i18n/account_fiscal_position_rule_sale.pot
odoo/addons/account_fiscal_position_rule_sale/i18n/ca.po
odoo/addons/account_fiscal_position_rule_sale/i18n/en_US.po
odoo/addons/account_fiscal_position_rule_sale/i18n/es.po
odoo/addons/account_fiscal_position_rule_sale/i18n/hu.po
odoo/addons/account_fiscal_position_rule_sale/i18n/pt_BR.po
odoo/addons/account_fiscal_position_rule_sale/i18n/sl.po
odoo/addons/account_fiscal_position_rule_sale/models/__init__.py
odoo/addons/account_fiscal_position_rule_sale/models/sale.py
odoo/addons/account_fiscal_position_rule_sale/readme/CONTRIBUTORS.rst
odoo/addons/account_fiscal_position_rule_sale/readme/DESCRIPTION.rst
odoo/addons/account_fiscal_position_rule_sale/security/ir.model.access.csv
odoo/addons/account_fiscal_position_rule_sale/static/description/icon.png
odoo/addons/account_fiscal_position_rule_sale/static/description/index.html
odoo/addons/account_fiscal_position_rule_sale/tests/__init__.py
odoo/addons/account_fiscal_position_rule_sale/tests/test_account_fiscal_position_rule_sale.py
odoo13_addon_account_fiscal_position_rule_sale-13.0.1.0.1.dist-info/METADATA
odoo13_addon_account_fiscal_position_rule_sale-13.0.1.0.1.dist-info/WHEEL
odoo13_addon_account_fiscal_position_rule_sale-13.0.1.0.1.dist-info/top_level.txt
odoo13_addon_account_fiscal_position_rule_sale-13.0.1.0.1.dist-info/RECORD
